Metadata-Version: 1.1
Name: SuperWires
Version: 0.9.2
Summary: Rewriting of the graphics library in 'Python for the Absolute Beginner' book.
Home-page: http://www.supernovaapps.com/
Author: Akif Patel
Author-email: superwires@supernovaapps.com
License: Apache 2.0
Keywords: livewires python graphics pygame library
Platform: UNKNOWN
Classifier: Development Status :: 3 - Alpha
Classifier: License :: OSI Approved :: Apache Software License
Classifier: Programming Language :: Python
Classifier: Topic :: Multimedia :: Graphics
